kumpeapi.py
kumpeapi-1.0.8.dist-info/METADATA
kumpeapi-1.0.8.dist-info/WHEEL
kumpeapi-1.0.8.dist-info/licenses/LICENSE
kumpeapi-1.0.8.dist-info/RECORD
