Metadata-Version: 2.1
Name: kumpeapi
Version: 1.0.8
Summary: KumpeAPI Functions
Author-email: KumpeApps LLC <jakumpe@kumpes.com>
License-Expression: GPL-3.0
License-File: LICENSE
Classifier: License :: OSI Approved :: GNU General Public License v3 (GPLv3)
Classifier: Natural Language :: English
Classifier: Operating System :: OS Independent
Classifier: Programming Language :: Python :: 3
Requires-Python: >=3.7
Requires-Dist: datetime
Requires-Dist: flask
Requires-Dist: pymysql
Requires-Dist: requests
